{"cameraMode":{"drawMode":0,"name":"Shaded","section":"Shading Mode"},"sceneLighting":true,"audioPlay":false,"sceneViewState":{"showFog":true,"showMaterialUpdate":false,"showSkybox":true,"showFlares":true,"showImageEffects":true,"showParticleSystems":true},"in2DMode":false,"pivot":{"x":3.8492796421051027,"y":-5.4498066902160648,"z":25.290719985961915},"rotation":{"x":0.11826243251562119,"y":0.06815239042043686,"z":-0.008091675117611885,"w":0.9906755089759827},"size":30.090932846069337,"orthographic":false}